zombase/__init__.py
zombase/cli.py
zombase/config.py
zombase/database.py
zombase/errors.py
zombase/foreman.py
zombase/mail.py
zombase/mapping.py
zombase/validation.py
zombase/worker.py
zombase-0.8.1.dist-info/DESCRIPTION.rst
zombase-0.8.1.dist-info/METADATA
zombase-0.8.1.dist-info/RECORD
zombase-0.8.1.dist-info/WHEEL
zombase-0.8.1.dist-info/metadata.json
zombase-0.8.1.dist-info/top_level.txt
