Metadata-Version: 2.0
Name: zombase
Version: 0.8.1
Summary: A toolset to build beautiful data layer APIs
Home-page: UNKNOWN
Author: Bastien Gandouet
Author-email: bastien@mozaiqu.es
License: MIT
Platform: UNKNOWN
Classifier: Development Status :: 3 - Alpha
Classifier: Intended Audience :: Developers
Classifier: License :: OSI Approved :: MIT License
Classifier: Operating System :: OS Independent
Classifier: Programming Language :: Python
Classifier: Programming Language :: Python :: 3
Classifier: Topic :: Software Development :: Libraries :: Python Modules
Requires-Dist: SQLAlchemy (>=1.0)
Requires-Dist: voluptuous (>=0.8)
Requires-Dist: six (>=1.10)
